README.rst
setup.cfg
setup.py
hyperkite/__init__.py
hyperkite/constants.py
hyperkite/hyperkite.py
hyperkite.egg-info/PKG-INFO
hyperkite.egg-info/SOURCES.txt
hyperkite.egg-info/dependency_links.txt
hyperkite.egg-info/not-zip-safe
hyperkite.egg-info/requires.txt
hyperkite.egg-info/top_level.txt