Metadata-Version: 1.1
Name: hyperkite
Version: 0.1.5
Summary: Hyperkite is a parameter optimization tool inspired by the way you train your machine learning models. From academia to industry, the tool is designed to optimize hyper-parameters and manage machine learning training experiments, using the most powerful algorithms in the most simple way.
Home-page: https://github.com/Hyperkite/hyperkite
Author: Hyperkite
Author-email: admin@hyperkite.ai
License: MIT
Download-URL: https://github.com/Hyperkite/hyperkite/archive/v0.1.2.tar.gz
Keywords: hyper-parameter,optimization,tool,bayesian
Platform: UNKNOWN
Classifier: Development Status :: 3 - Alpha
Classifier: Intended Audience :: Developers
Classifier: Topic :: Software Development :: Build Tools
Classifier: License :: OSI Approved :: MIT License
Classifier: Programming Language :: Python :: 3
Classifier: Programming Language :: Python :: 3.4
Classifier: Programming Language :: Python :: 3.5
Classifier: Programming Language :: Python :: 3.6
